exdpn/__init__.py
exdpn/data_petri_net/__init__.py
exdpn/data_petri_net/data_petri_net.py
exdpn/data_preprocessing/__init__.py
exdpn/data_preprocessing/data_preprocessing.py
exdpn/decisionpoints/__init__.py
exdpn/decisionpoints/find.py
exdpn/guard_datasets/__init__.py
exdpn/guard_datasets/data_extraction.py
exdpn/guards/__init__.py
exdpn/guards/decision_tree_guard.py
exdpn/guards/guard.py
exdpn/guards/guard_manager.py
exdpn/guards/logistic_regression_guard.py
exdpn/guards/ml_technique.py
exdpn/guards/model_builder.py
exdpn/guards/neural_network_guard.py
exdpn/guards/random_forest_guard.py
exdpn/guards/svm_guard.py
exdpn/guards/xgboost_guard.py
exdpn/petri_net/__init__.py
exdpn/petri_net/get_petri_net.py
exdpn/util/__init__.py
exdpn/util/util.py
tests/__init__.py
tests/data_petri_net/__init__.py
tests/data_petri_net/data_petri_net.py
tests/data_petri_net/data_petri_net_mean_conformance.py
tests/data_preprocessing/__init__.py
tests/data_preprocessing/data_preprocessing.py
tests/decisionpoints/__init__.py
tests/decisionpoints/find_test.py
tests/guard_datasets/__init__.py
tests/guard_datasets/get_all_guard_datasets_test.py
tests/guards/__init__.py
tests/guards/guard_manager.py
tests/guards/xgboost_guard.py
tests/util/__init__.py
tests/util/extend_log_with_preceding_event_delay.py
tests/util/extend_log_with_total_elapsed_time.py
exdpn-1.1.1.dist-info/COPYING
exdpn-1.1.1.dist-info/METADATA
exdpn-1.1.1.dist-info/WHEEL
exdpn-1.1.1.dist-info/top_level.txt
exdpn-1.1.1.dist-info/RECORD
