Metadata-Version: 2.1
Name: exdpn
Version: 1.1.1
Summary: Tool to mine and evaluate explainable data Petri nets using different classification techniques.
Author: marairis, aarkue, cpitsch, jonathansc
License: GPLv3
Project-URL: Documentation, https://aarkue.github.io/eXdpn/
Project-URL: GitHub, https://github.com/aarkue/eXdpn
Keywords: Process mining,Data Petri net
Platform: any
Classifier: Programming Language :: Python :: 3
Classifier: Operating System :: OS Independent
Classifier: License :: OSI Approved :: GNU General Public License v3 (GPLv3)
License-File: COPYING
Requires-Dist: pm4py (~=2.2.27)
Requires-Dist: xgboost (~=1.6.0)
Requires-Dist: shap (~=0.41.0)
Requires-Dist: scikit-learn (~=1.1.1)
Requires-Dist: pandas (~=1.3.5)
Requires-Dist: numpy (~=1.21.6)
Requires-Dist: matplotlib (~=3.5.2)
